mchextract/__init__.py
mchextract/api.py
mchextract/cli.py
mchextract/commandline.py
mchextract/consts.py
mchextract/data_downloader.py
mchextract/downloader.py
mchextract/dwhconverter.py
mchextract/exceptions.py
mchextract/logging_config.py
mchextract/metadata_loader.py
mchextract/models.py
mch_extract-0.2.1.dist-info/METADATA
mch_extract-0.2.1.dist-info/WHEEL
mch_extract-0.2.1.dist-info/entry_points.txt
mch_extract-0.2.1.dist-info/licenses/LICENSE
mch_extract-0.2.1.dist-info/RECORD
