Metadata-Version: 2.4
Name: mch-extract
Version: 0.2.1
Summary: A Python package for extracting meteorological data from MeteoSwiss OpenData API
Project-URL: Homepage, https://github.com/martintops/mch-extract
Project-URL: Repository, https://github.com/martintops/mch-extract
Project-URL: Issues, https://github.com/martintops/mch-extract/issues
Project-URL: Documentation, https://github.com/martintops/mch-extract#readme
Author-email: Martin Spoto <martin.spoto98@gmail.com>
License-File: LICENSE
Keywords: data,meteorology,meteoswiss,ogd,switzerland,weather
Classifier: Development Status :: 4 - Beta
Classifier: Intended Audience :: Science/Research
Classifier: License :: OSI Approved :: MIT License
Classifier: Programming Language :: Python :: 3
Classifier: Programming Language :: Python :: 3.10
Classifier: Programming Language :: Python :: 3.11
Classifier: Programming Language :: Python :: 3.12
Classifier: Topic :: Scientific/Engineering :: Atmospheric Science
Requires-Python: >=3.10
Requires-Dist: more-itertools>=10.7.0
Requires-Dist: polars-lts-cpu>=1.31.0
Requires-Dist: requests>=2.32.4
